yt_download/__init__.py
yt_download/config.py
yt_download/yt_download.py
yt_download-0.1.1.dist-info/LICENSE
yt_download-0.1.1.dist-info/METADATA
yt_download-0.1.1.dist-info/WHEEL
yt_download-0.1.1.dist-info/entry_points.txt
yt_download-0.1.1.dist-info/top_level.txt
yt_download-0.1.1.dist-info/RECORD
